LICENSE
README.md
setup.py
tests/__init__.py
tests/test.py
website_status_checker/__init__.py
website_status_checker/checker.py
wstatus.egg-info/PKG-INFO
wstatus.egg-info/SOURCES.txt
wstatus.egg-info/dependency_links.txt
wstatus.egg-info/entry_points.txt
wstatus.egg-info/requires.txt
wstatus.egg-info/top_level.txt