Metadata-Version: 2.1
Name: wstatus
Version: 1.0
Summary: Una herramienta que verifica si una lista de sitios web está activa y disponible.
Home-page: https://github.com/diegoamengarelli/web_status_checker
Author: Diego Mengarelli
Author-email: diegoamengarelli@gmail.com
Requires-Python: >=3.9
License-File: LICENSE
